seismicprocesspy/__init__.py
seismicprocesspy/trim.py
seismicprocesspy/convert/__init__.py
seismicprocesspy/convert/fromDeepSoil.py
seismicprocesspy/convert/timestep.py
seismicprocesspy/process/__init__.py
seismicprocesspy/process/aligned-format.py
seismicprocesspy/process/change-time-step.py
seismicprocesspy/process/trim.py
seismicprocesspy-0.1.2.dist-info/METADATA
seismicprocesspy-0.1.2.dist-info/WHEEL
seismicprocesspy-0.1.2.dist-info/top_level.txt
seismicprocesspy-0.1.2.dist-info/RECORD
